source_sendgrid/__init__.py
source_sendgrid/config_migrations.py
source_sendgrid/manifest.yaml
source_sendgrid/run.py
source_sendgrid/schemas/contacts.json
source_sendgrid/source.py
airbyte_source_sendgrid-1.1.5.dist-info/METADATA
airbyte_source_sendgrid-1.1.5.dist-info/WHEEL
airbyte_source_sendgrid-1.1.5.dist-info/entry_points.txt
airbyte_source_sendgrid-1.1.5.dist-info/RECORD
