Metadata-Version: 2.1
Name: airbyte-source-sendgrid
Version: 1.1.5
Summary: Source implementation for Sendgrid.
Home-page: https://airbyte.com
License: MIT
Author: Airbyte
Author-email: contact@airbyte.io
Requires-Python: >=3.10,<3.12
Classifier: License :: OSI Approved :: MIT License
Classifier: Programming Language :: Python :: 3
Classifier: Programming Language :: Python :: 3.10
Classifier: Programming Language :: Python :: 3.11
Requires-Dist: airbyte_cdk (>=5,<6)
Requires-Dist: pandas (>=2.1.1,<3.0.0)
Project-URL: Documentation, https://docs.airbyte.com/integrations/sources/sendgrid
Project-URL: Repository, https://github.com/airbytehq/airbyte
